{
  "data": {
    "icon_close": {
      "data": {
        "alt_text": null,
        "credit": null,
        "description": null,
        "look_number": null,
        "title": null,
        "width": null,
        "svg_content": "<svg xmlns=\"http://www.w3.org/2000/svg\" viewBox=\"0 0 18.02 17.98\"><title>close</title><path d=\"M18.02 1.42L16.61 0l-7.6 7.58L1.41 0 0 1.42l7.59 7.57L0 16.56l1.41 1.42 7.6-7.58 7.6 7.58 1.41-1.42-7.59-7.57 7.59-7.57z\"/></svg>"
      },
      "state": {
        "is_image": false,
        "is_picture": false,
        "is_static": false,
        "is_svg": true,
        "is_linked": false,
        "is_landscape": false,
        "is_portrait": false,
        "is_square": false,
        "is_lazyload": false
      },
      "style": {
        "cls": "",
        "inline": ""
      },
      "translation": {},
      "type": "SVG"
    },
    "message": "Welcome to British Vogue. This site uses cookies to improve your experience and deliver personalised advertising. You can <a href=\"https://www.condenast.co.uk/cookie-notice/?utm_source=British%20Vogue&utm_campaign=cookie%20warning&utm_medium=referral#opting_out_of_cookies\">opt out</a> at any time or find out more by reading our <a href=\"https://www.condenast.co.uk/cookie-notice/?utm_source=British%20Vogue&utm_campaign=cookie warning&utm_medium=referral\">cookie policy</a>."
  },
  "state": {},
  "style": {
    "cls": "",
    "inline": ""
  },
  "translation": {},
  "type": "CookieWarning"
}