{
  "data": {
    "byline": "Katie Berrington and Sam Rogers",
    "image": {
      "data": {
        "alt_text": null,
        "credit": null,
        "description": "",
        "image_url": "http://vg.staging.www.condenet.co.uk/image/wb1WgznWwr8/crop/405",
        "lazyload": true,
        "look_number": null,
        "sources": [{
          "media": "(min-width: 800px)",
          "srcset": "http://vg.staging.www.condenet.co.uk/image/wb1WgznWwr8/crop/405/0.5625 405w, http://vg.staging.www.condenet.co.uk/image/wb1WgznWwr8/crop/810/0.5625 810w, http://vg.staging.www.condenet.co.uk/image/wb1WgznWwr8/crop/1020/0.5625 1020w, http://vg.staging.www.condenet.co.uk/image/wb1WgznWwr8/crop/1440/0.5625 1440w, http://vg.staging.www.condenet.co.uk/image/wb1WgznWwr8/crop/1620/0.5625 1620w"
        }, {
          "media": "(min-width: 0px)",
          "srcset": "http://vg.staging.www.condenet.co.uk/image/wb1WgznWwr8/crop/405 405w, http://vg.staging.www.condenet.co.uk/image/wb1WgznWwr8/crop/810 810w, http://vg.staging.www.condenet.co.uk/image/wb1WgznWwr8/crop/1020 1020w, http://vg.staging.www.condenet.co.uk/image/wb1WgznWwr8/crop/1440 1440w, http://vg.staging.www.condenet.co.uk/image/wb1WgznWwr8/crop/1620 1620w"
        }],
        "title": ""
      },
      "state": {
        "is_image": false,
        "is_linked": false,
        "is_picture": true,
        "is_static": false,
        "is_svg": false
      },
      "style": {
        "cls": "img-lazyload "
      },
      "type": "Picture"
    },
    "link": {
      "data": {
        "title": "Golden Globes 2017",
        "url": "http://vg.staging.www.condenet.co.uk/gallery/golden-globe-awards-2017"
      },
      "state": {},
      "style": {
        "cls": ""
      },
      "type": "Link"
    },
    "meta_list": {
      "data": {
        "items": [{
          "data": {
            "item": {
              "data": {
                "icon": null,
                "link": {
                  "data": {
                    "title": "Golden Globes",
                    "url": "http://vg.staging.www.condenet.co.uk/event/golden-globes/"
                  },
                  "state": {},
                  "style": {
                    "cls": ""
                  },
                  "type": "Link"
                },
                "meta_type": "tag",
                "title": "Golden Globes"
              },
              "state": {},
              "style": {
                "cls": ""
              },
              "type": "Meta"
            }
          },
          "state": {},
          "style": {
            "cls": ""
          },
          "type": "ListItem"
        }, {
          "data": {
            "item": {
              "data": {
                "icon": null,
                "link": null,
                "meta_type": "date",
                "title": "09 Jan 2017"
              },
              "state": {},
              "style": {
                "cls": ""
              },
              "type": "Meta"
            }
          },
          "state": {},
          "style": {
            "cls": ""
          },
          "type": "ListItem"
        }],
        "length": 2
      },
      "state": {},
      "style": {
        "cls": ""
      },
      "type": "List"
    },
    "profiles": [{
      "data": {
        "bio": "Katie is the acting news editor of Vogue.co.uk",
        "link": {
          "data": {
            "title": "Katie Berrington",
            "url": "http://vg.staging.www.condenet.co.uk/profile/katie-berrington/"
          },
          "state": {},
          "style": {
            "cls": ""
          },
          "type": "Link"
        },
        "name": "Katie Berrington",
        "teaser": "Katie is the acting news editor of Vogue.co.uk"
      },
      "state": {},
      "style": {
        "cls": ""
      },
      "type": "Profile"
    }, {
      "data": {
        "bio": "Sam is acting editor of Vogue.co.uk",
        "link": {
          "data": {
            "title": "Sam Rogers",
            "url": "http://vg.staging.www.condenet.co.uk/profile/sam-rogers/"
          },
          "state": {},
          "style": {
            "cls": ""
          },
          "type": "Link"
        },
        "name": "Sam Rogers",
        "teaser": "Sam is acting editor of Vogue.co.uk"
      },
      "state": {},
      "style": {
        "cls": ""
      },
      "type": "Profile"
    }],
    "sponsor": null,
    "tag": {
      "data": {
        "event_information": null,
        "link": {
          "data": {
            "title": "Golden Globes",
            "url": "http://vg.staging.www.condenet.co.uk/event/golden-globes/"
          },
          "state": {},
          "style": {
            "cls": ""
          },
          "type": "Link"
        },
        "title": "Golden Globes"
      },
      "state": {},
      "style": {
        "cls": ""
      },
      "type": "Tag"
    },
    "teaser": "Catch up with all the red-carpet action from the Golden Globes 2017",
    "title": "Golden Globes 2017"
  },
  "state": {},
  "style": {
    "cls": ""
  },
  "type": "SectionSuperfeature"
}